inbound/__init__.py
inbound/bus.py
inbound/callback.py
inbound/envelope.py
inbound/event.py
inbound/py.typed
inbound/stream.py
inbound/utils.py
inbound/brokers/__init__.py
inbound/brokers/amqp.py
inbound/brokers/base.py
inbound/brokers/kafka.py
inbound/brokers/memory.py
inbound/serializers/__init__.py
inbound/serializers/base.py
inbound/serializers/jsons.py
inbound/serializers/msgpacks.py
inbound/serializers/noop.py
python_inbound-1.0.11.dist-info/METADATA
python_inbound-1.0.11.dist-info/WHEEL
python_inbound-1.0.11.dist-info/licenses/LICENSE
python_inbound-1.0.11.dist-info/RECORD
