Metadata-Version: 2.4
Name: python-inbound
Version: 1.0.11
Summary: An Event Bus framework for event driven systems.
Project-URL: repository, https://gitlab.com/emergentmethods/python-inbound
Author-email: Tim Pogue <tim@emergentmethods.ai>
License: MIT
License-File: LICENSE
Requires-Python: <4.0,>=3.10
Requires-Dist: cloudevents>=1.11.0
Requires-Dist: msgpack>=1.0.8
Requires-Dist: orjson>=3.10.12
Requires-Dist: pydantic>=2.9.2
Provides-Extra: amqp
Requires-Dist: aio-pika>=9.5.0; extra == 'amqp'
Provides-Extra: kafka
Requires-Dist: aiokafka>=0.12.0; extra == 'kafka'
